<?xml version="1.0" encoding="UTF-8"?>
<objects serializationModel="Studio.02.02.00">
	<object class="MixerMaster" id="{34652ddb-61f7-4d53-9613-92f7af1a945e}">
		<property name="name">
			<value>Master Bus</value>
		</property>
		<relationship name="effectChain">
			<destination>{7b034a08-3795-4bb9-ba79-f555d331066a}</destination>
		</relationship>
		<relationship name="panner">
			<destination>{98275c3f-513a-45e3-8bf5-e2c4f6852fa4}</destination>
		</relationship>
		<relationship name="mixer">
			<destination>{16588baa-ef4f-48cd-88cd-8b8de462da62}</destination>
		</relationship>
	</object>
	<object class="MixerBusEffectChain" id="{7b034a08-3795-4bb9-ba79-f555d331066a}">
		<relationship name="effects">
			<destination>{f176d1e9-3fe8-448c-a406-474700d12e4f}</destination>
		</relationship>
	</object>
	<object class="MixerBusPanner" id="{98275c3f-513a-45e3-8bf5-e2c4f6852fa4}">
		<property name="overridingOutputFormat">
			<value>2</value>
		</property>
	</object>
	<object class="MixerBusFader" id="{f176d1e9-3fe8-448c-a406-474700d12e4f}" />
</objects>
